httpchain/__init__.py
httpchain/v1/__init__.py
httpchain/v1/executor.py
httpchain/v1/extractor_engine.py
httpchain/v1/header_randomizer.py
httpchain/v1/request_executor.py
httpchain/v1/schema.py
httpchain/v1/step_executor.py
httpchain/v1/variable_manager.py
httpchain-1.0.1.dist-info/METADATA
httpchain-1.0.1.dist-info/WHEEL
httpchain-1.0.1.dist-info/licenses/LICENSE
httpchain-1.0.1.dist-info/RECORD
