Metadata-Version: 2.4
Name: httpchain
Version: 1.0.1
Summary: Declarative HTTP workflow engine for building complex API request chains with dependency management and data extraction
Project-URL: Homepage, https://github.com/jatin-dot-py/httpchain
Project-URL: Documentation, https://github.com/jatin-dot-py/httpchain#readme
Project-URL: Repository, https://github.com/jatin-dot-py/httpchain
Project-URL: Issues, https://github.com/jatin-dot-py/httpchain/issues
Author: Jatin Banga
License: MIT
License-File: LICENSE
Keywords: api,automation,http,osint,web-scraping,workflow
Classifier: Development Status :: 4 - Beta
Classifier: Intended Audience :: Developers
Classifier: License :: OSI Approved :: MIT License
Classifier: Programming Language :: Python :: 3
Classifier: Programming Language :: Python :: 3.10
Classifier: Programming Language :: Python :: 3.11
Classifier: Programming Language :: Python :: 3.12
Classifier: Topic :: Internet :: WWW/HTTP
Classifier: Topic :: Software Development :: Libraries :: Python Modules
Requires-Python: >=3.10
Requires-Dist: brotli>=1.1.0
Requires-Dist: bs4>=0.0.2
Requires-Dist: httpx>=0.28.1
Requires-Dist: json5>=0.12.1
Requires-Dist: jsonpath-ng>=1.7.0
Requires-Dist: lxml>=6.0.2
Requires-Dist: requests>=2.32.5
Provides-Extra: dev
Requires-Dist: tldextract>=5.1.2; extra == 'dev'
Provides-Extra: examples
Requires-Dist: tldextract>=5.1.2; extra == 'examples'
